database_automation/__init__.py
database_automation/mongo_crud.py
mongoauto-0.0.3.dist-info/METADATA
mongoauto-0.0.3.dist-info/WHEEL
mongoauto-0.0.3.dist-info/top_level.txt
mongoauto-0.0.3.dist-info/RECORD
